README.rst
setup.py
filequeue/__init__.py
filequeue/filequeue.py
filequeue.egg-info/PKG-INFO
filequeue.egg-info/SOURCES.txt
filequeue.egg-info/dependency_links.txt
filequeue.egg-info/top_level.txt