Metadata-Version: 1.1
Name: filequeue
Version: 0.4.1
Summary: A thread-safe queue object which is interchangeable with the stdlib Queue. Any overflow goes into a compressed file to keep excessive amounts of queued items out of memory
Home-page: http://pypi.python.org/pypi/filequeue
Author: Paul Wiseman
Author-email: poalman@gmail.com
License: BSD
Keywords: queue thread-safe file gzip
Platform: UNKNOWN
Classifier: Development Status :: 3 - Alpha
Classifier: Intended Audience :: Developers
Classifier: Topic :: Utilities
Classifier: Programming Language :: Python :: 2
Classifier: Programming Language :: Python :: 2.5
Classifier: Programming Language :: Python :: 2.6
Classifier: Programming Language :: Python :: 2.7
Classifier: Programming Language :: Python :: 3
Classifier: Programming Language :: Python :: 3.0
Classifier: Programming Language :: Python :: 3.1
Classifier: Programming Language :: Python :: 3.2
Classifier: Programming Language :: Python :: 3.3
Classifier: Programming Language :: Python :: 3.4
Classifier: Programming Language :: Python :: 3.5
Classifier: Programming Language :: Python :: 3.6
Classifier: Programming Language :: Python :: 3.7
Classifier: License :: OSI Approved :: BSD License
